Map_Helper/MapHelper.py
Map_Helper/__init__.py
map_helper-1.0.0.dist-info/METADATA
map_helper-1.0.0.dist-info/WHEEL
map_helper-1.0.0.dist-info/entry_points.txt
map_helper-1.0.0.dist-info/licenses/LICENSE.txt
map_helper-1.0.0.dist-info/RECORD
