Metadata-Version: 2.1
Name: Map_Helper
Version: 1.0.0
Summary: A Tool for Helping with Flood Maps
Author-email: Jacob Tilstra <tilstra15@gmail.com>
License-File: LICENSE.txt
Classifier: License :: OSI Approved :: MIT License
Classifier: Operating System :: Microsoft :: Windows
Classifier: Programming Language :: Python :: 3
Requires-Python: >=3.8
Requires-Dist: haversine
Requires-Dist: matplotlib
Requires-Dist: pandas
Requires-Dist: path-py
Requires-Dist: pymupdf
Requires-Dist: pywin32
Requires-Dist: selenium
Requires-Dist: simplekml
Requires-Dist: urllib3
